shush/__init__.py
shush/pytest.py
shush-0.3.2.dist-info/METADATA
shush-0.3.2.dist-info/WHEEL
shush-0.3.2.dist-info/RECORD
