Metadata-Version: 2.1
Name: shush
Version: 0.3.2
Summary: Subprocesses for humans.
License: ISC
Author: John Freeman
Author-email: jfreeman08@gmail.com
Requires-Python: >=3.9,<4.0
Classifier: License :: OSI Approved
Classifier: Programming Language :: Python :: 3
Classifier: Programming Language :: Python :: 3.9
Classifier: Programming Language :: Python :: 3.10
Classifier: Programming Language :: Python :: 3.11
